langroid/__init__.py
langroid/mytypes.py
langroid/agent/__init__.py
langroid/agent/base.py
langroid/agent/batch.py
langroid/agent/chat_agent.py
langroid/agent/chat_document.py
langroid/agent/openai_assistant.py
langroid/agent/task.py
langroid/agent/tool_message.py
langroid/agent/callbacks/__init__.py
langroid/agent/callbacks/chainlit.py
langroid/agent/special/__init__.py
langroid/agent/special/doc_chat_agent.py
langroid/agent/special/lance_doc_chat_agent.py
langroid/agent/special/lance_tools.py
langroid/agent/special/relevance_extractor_agent.py
langroid/agent/special/retriever_agent.py
langroid/agent/special/table_chat_agent.py
langroid/agent/special/lance_rag/__init__.py
langroid/agent/special/lance_rag/critic_agent.py
langroid/agent/special/lance_rag/lance_rag_task.py
langroid/agent/special/lance_rag/query_planner_agent.py
langroid/agent/special/neo4j/__init__.py
langroid/agent/special/neo4j/csv_kg_chat.py
langroid/agent/special/neo4j/neo4j_chat_agent.py
langroid/agent/special/neo4j/utils/__init__.py
langroid/agent/special/neo4j/utils/system_message.py
langroid/agent/special/sql/__init__.py
langroid/agent/special/sql/sql_chat_agent.py
langroid/agent/special/sql/utils/__init__.py
langroid/agent/special/sql/utils/description_extractors.py
langroid/agent/special/sql/utils/populate_metadata.py
langroid/agent/special/sql/utils/system_message.py
langroid/agent/special/sql/utils/tools.py
langroid/agent/tools/__init__.py
langroid/agent/tools/duckduckgo_search_tool.py
langroid/agent/tools/google_search_tool.py
langroid/agent/tools/metaphor_search_tool.py
langroid/agent/tools/recipient_tool.py
langroid/agent/tools/retrieval_tool.py
langroid/agent/tools/segment_extract_tool.py
langroid/cachedb/__init__.py
langroid/cachedb/base.py
langroid/cachedb/momento_cachedb.py
langroid/cachedb/redis_cachedb.py
langroid/embedding_models/__init__.py
langroid/embedding_models/base.py
langroid/embedding_models/models.py
langroid/embedding_models/remote_embeds.py
langroid_slim-0.1.255.dist-info/LICENSE
langroid_slim-0.1.255.dist-info/METADATA
langroid_slim-0.1.255.dist-info/WHEEL
langroid_slim-0.1.255.dist-info/top_level.txt
langroid_slim-0.1.255.dist-info/RECORD
