Metadata-Version: 2.1
Name: langroid-slim
Version: 0.1.255
Summary: Harness LLMs with Multi-Agent Programming
Author: Prasad Chalasani
Author-email: pchalasani@gmail.com
License: MIT
Requires-Python: >=3.10, <3.12
License-File: LICENSE
Requires-Dist: onnxruntime ==1.16.1
Requires-Dist: fire >=0.5.0
Requires-Dist: bs4 >=0.0.1
Requires-Dist: python-dotenv >=1.0.0
Requires-Dist: wget >=3.2
Requires-Dist: rich >=13.3.4
Requires-Dist: requests-oauthlib >=1.3.1
Requires-Dist: halo >=0.0.31
Requires-Dist: typer >=0.9.0
Requires-Dist: colorlog >=6.7.0
Requires-Dist: openai >=1.14.0
Requires-Dist: tiktoken >=0.7.0
Requires-Dist: pygithub >=1.58.1
Requires-Dist: pygments >=2.15.1
Requires-Dist: redis >=5.0.1
Requires-Dist: fakeredis >=2.12.1
Requires-Dist: requests >=2.31.0
Requires-Dist: types-redis >=4.5.5.2
Requires-Dist: types-requests >=2.31.0.1
Requires-Dist: pyparsing >=3.0.9
Requires-Dist: nltk >=3.8.1
Requires-Dist: qdrant-client >=1.8.0
Requires-Dist: pydantic ==1.10.13
Requires-Dist: pandas >=2.1.3
Requires-Dist: pyyaml >=6.0
Requires-Dist: rank-bm25 >=0.2.2
Requires-Dist: groq >=0.5.0
Requires-Dist: jinja2 >=3.1.2
Requires-Dist: docstring-parser >=0.15
Requires-Dist: faker >=18.9.0
Requires-Dist: thefuzz ==0.20.0
Requires-Dist: aiohttp >=3.9.1
Provides-Extra: docs
Requires-Dist: mkdocs >=1.4.2 ; extra == 'docs'
Requires-Dist: mkdocs-material >=9.1.5 ; extra == 'docs'
Requires-Dist: mkdocstrings[python] >=0.21.2 ; extra == 'docs'
Requires-Dist: mkdocs-awesome-pages-plugin >=2.8.0 ; extra == 'docs'
Requires-Dist: mkdocs-rss-plugin >=1.8.0 ; extra == 'docs'
Requires-Dist: mkdocs-gen-files >=0.4.0 ; extra == 'docs'
Requires-Dist: mkdocs-literate-nav >=0.6.0 ; extra == 'docs'
Requires-Dist: mkdocs-section-index >=0.3.5 ; extra == 'docs'
Requires-Dist: mkdocs-jupyter >=0.24.1 ; extra == 'docs'
Requires-Dist: chromadb <=0.4.23,>=0.4.21 ; extra == 'docs'
Provides-Extra: extra
Requires-Dist: ruff >=0.2.2 ; extra == 'extra'
Requires-Dist: pre-commit >=3.3.2 ; extra == 'extra'
Requires-Dist: flake8 >=6.0.0 ; extra == 'extra'
Requires-Dist: mypy >=1.7.0 ; extra == 'extra'
Requires-Dist: black[jupyter] >=24.3.0 ; extra == 'extra'
Requires-Dist: autopep8 >=2.0.2 ; extra == 'extra'
